Metadata-Version: 1.0
Name: num-distributions
Version: 0.1
Summary: Gaussian and Binomial distributions
Home-page: UNKNOWN
Author: Raj Vaghashiya
Author-email: rajvaghasiya*****@gmail.com
License: UNKNOWN
Platform: UNKNOWN
